ewslib_core/ews_env/__init__.py
ewslib_core/ews_env/version.py
ewslib_core_ews_env-0.1.1.dist-info/LICENSE
ewslib_core_ews_env-0.1.1.dist-info/METADATA
ewslib_core_ews_env-0.1.1.dist-info/WHEEL
ewslib_core_ews_env-0.1.1.dist-info/top_level.txt
ewslib_core_ews_env-0.1.1.dist-info/RECORD
