Metadata-Version: 2.1
Name: ewslib-core-ews-env
Version: 0.1.1
Summary: EWS Library Environnemnt  management
Author-email: EWS Consulting - Testing Center <f.farella@ews-consulting.at>
License: MIT License
Project-URL: Homepage, https://github.com/EWS-Consulting-Private/ewslib-core-ews-env
Project-URL: Documentation, http://cm.ews.local/mb/ewslib-core-ews-env
Project-URL: Source, https://github.com/EWS-Consulting-Private/ewslib-core-ews-env
Classifier: Development Status :: 4 - Beta
Classifier: Intended Audience :: Developers
Classifier: Intended Audience :: Science/Research
Classifier: License :: OSI Approved :: MIT License
Classifier: Operating System :: Unix
Classifier: Programming Language :: Python :: 3
Classifier: Programming Language :: Python :: 3.9
Classifier: Programming Language :: Python :: 3.10
Classifier: Programming Language :: Python :: 3.11
Classifier: Programming Language :: Python
Classifier: Topic :: Software Development :: Quality Assurance
Classifier: Topic :: Software Development :: Libraries :: Python Modules
Classifier: Typing :: Typed
Requires-Python: >=3.9
License-File: LICENSE
Requires-Dist: tomli ; python_version < "3.11"
Requires-Dist: typing-extensions ; python_version < "3.11"
